{
  "candidate_check": {
    "check": {
      "command": "powershell -NoProfile -Command \"$os=Get-CimInstance Win32_OperatingSystem; if ($os.Caption -like '*Windows Server 2019*' -and [int]$os.BuildNumber -ge 17763) { 'Compliant' }\"",
      "type": "command_output"
    },
    "description": "Windows Server 2019 must be maintained at a supported servicing level.",
    "expected": {
      "type": "equals",
      "value": "Compliant"
    },
    "platform": "windows",
    "vuln_id": "V-205849"
  },
  "check_content_excerpt": "Open \"Command Prompt\".\n\nEnter \"winver.exe\".\n\nIf the \"About Windows\" dialog box does not display \"Microsoft Windows Server Version 1809 (Build 17763.xxx)\" or greater, this is a finding.\n\nPreview versions must not be used in a production environment.",
  "classification": "automated",
  "collector_commands": [],
  "collector_type": "windows_collector",
  "evaluator": "candidate_template",
  "evidence_fields": [
    "rule_id",
    "vuln_id",
    "status",
    "evidence",
    "source_artifact"
  ],
  "expected_values": {
    "type": "equals",
    "value": "Compliant"
  },
  "external_acceptance_refs": [],
  "fix_text_excerpt": "Update the system to a Version 1809 (Build 17763.xxx) or greater.",
  "fixtures": [],
  "implementation_status": "planned",
  "na_conditions": [],
  "normalizer": "command_output",
  "remediation": "planned",
  "rule_id": "SV-205849r991589_rule",
  "severity": "high",
  "source_benchmark": "",
  "source_coverage_manifest": "content/coverage/disa-authoritative/windows_server_2019_stig/u_ms_windows_server_2019_v3r6_stig.json",
  "source_version": "U_MS_Windows_Server_2019_V3R6_STIG.zip",
  "stig_id": "Windows_Server_2019_STIG",
  "title": "Windows Server 2019 must be maintained at a supported servicing level.",
  "tracking_issue": "TODO-V-205849",
  "vuln_id": "V-205849"
}
