{
  "check_content_excerpt": "Note: The following instructions use the PGDATA and PGVER environment variables. See supplementary content APPENDIX-F for instructions on configuring PGDATA, APPENDIX-H for PGVER, and APPENDIX-I for PGLOG. Only the database owner and superuser can alter configuration of PostgreSQL.\n\nEnsure the PGLOG directory is owned by postgres user and group:\n\n$ sudo su - postgres\n$ ls -la ${PGLOG?}\u00a0\n\nIf PGLOG is not owned by the database owner, this is a finding.\u00a0\n\nEnsure the data directory is owned by postgres user and group.\u00a0\n\n$ sudo su - postgres\n$ ls -la ${PGDATA?}\n\nIf PGDATA is not owned by the database owner, this is a finding.\n\nEnsure pgaudit installation is owned by root:\n\n$ sudo su - postgres\n$ ls -la /usr/pgsql-${PGVER?}/share/contrib/pgaudit\n\nIf pgaudit installation is not owned by root, this is a finding.\n\nNext, as the database administrator (shown here as \"postgres\"), run the following SQL to list all roles and their privileges:\n\n$ sudo su - postgres\n$ psql -x -c \"\\du\"\n\nIf any role has \"superuser\" that should not, this is a finding.",
  "classification": "automated",
  "collector_commands": [],
  "collector_type": "platform_collector",
  "evaluator": "planned",
  "evidence_fields": [
    "rule_id",
    "vuln_id",
    "status",
    "evidence",
    "source_artifact"
  ],
  "expected_values": {},
  "external_acceptance_refs": [],
  "fix_text_excerpt": "Note: The following instructions use the PGDATA and PGVER environment variables. See supplementary content APPENDIX-F for instructions on configuring PGDATA, APPENDIX-H for PGVER and APPENDIX-I for PGLOG.\n\nIf PGLOG or PGDATA are not owned by postgres user and group, configure them as follows:\u00a0\n\n$ sudo chown -R postgres:postgres ${PGDATA?}\n$ sudo chown -R postgres:postgres ${PGLOG?}\n\nIf the pgaudit installation is not owned by root user and group, configure it as follows:\n\n$ sudo chown -R root:root /usr/pgsql-${PGVER?}/share/contrib/pgaudit\n\nTo remove superuser from a role, as the database administrator (shown here as \"postgres\"), run the following SQL:\n\n$ sudo su - postgres\n$ psql -c \"ALTER ROLE <role-name> WITH NOSUPERUSER\"",
  "fixtures": [],
  "implementation_status": "planned",
  "na_conditions": [],
  "normalizer": "planned",
  "remediation": "planned",
  "rule_id": "SV-233607r960939_rule",
  "severity": "medium",
  "source_benchmark": "",
  "source_coverage_manifest": "content/coverage/disa-authoritative/crunchy_data_postgresql_stig/u_cd_pgsql_v3r1_stig.json",
  "source_version": "U_CD_PGSQL_V3R1_STIG.zip",
  "stig_id": "Crunchy_Data_PostgreSQL_STIG",
  "title": "PostgreSQL must protect its audit features from unauthorized access.",
  "tracking_issue": "TODO-V-233607",
  "vuln_id": "V-233607"
}
