{
  "check_content_excerpt": "Verify the \"opensc-pcks11\" package is installed on the system by using the following command:  \n  \n     $ dpkg -l | grep opensc-pkcs11 \n     ii     opensc-pkcs11:amd64     0.22.0-1Ubuntu2     amd64     Smart card utilities with support for PKCS#15 compatible cards  \n  \nIf the \"opensc-pcks11\" package is not installed, this is a finding.",
  "classification": "automated",
  "collector_commands": [],
  "collector_type": "platform_collector",
  "evaluator": "planned",
  "evidence_fields": [
    "rule_id",
    "vuln_id",
    "status",
    "evidence",
    "source_artifact"
  ],
  "expected_values": {},
  "external_acceptance_refs": [],
  "fix_text_excerpt": "Install the \"opensc-pkcs11\" package by using the following command:  \n  \n     $ sudo apt-get install opensc-pkcs11",
  "fixtures": [],
  "implementation_status": "planned",
  "na_conditions": [],
  "normalizer": "planned",
  "remediation": "planned",
  "rule_id": "SV-260574r958816_rule",
  "severity": "medium",
  "source_benchmark": "",
  "source_coverage_manifest": "content/coverage/disa-authoritative/can_ubuntu_22_04_lts_stig/u_can_ubuntu_22_04_lts_v2r6_stig.json",
  "source_version": "U_CAN_Ubuntu_22-04_LTS_V2R6_STIG.zip",
  "stig_id": "CAN_Ubuntu_22-04_LTS_STIG",
  "title": "Ubuntu 22.04 LTS must accept personal identity verification (PIV) credentials.",
  "tracking_issue": "TODO-V-260574",
  "vuln_id": "V-260574"
}
