{
  "candidate_check": {
    "check": {
      "command": "powershell -NoProfile -Command \"$v=& httpd -v 2>$null | Select-String -Pattern 'Apache/(?<major>\\d+)\\.(?<minor>\\d+)' | Select-Object -First 1; $major=[int]$v.Matches[0].Groups['major'].Value; $minor=[int]$v.Matches[0].Groups['minor'].Value; if ($major -gt 2 -or ($major -eq 2 -and $minor -ge 4)) { 'Compliant' }\"",
      "type": "command_output"
    },
    "description": "The Apache web server software must be a vendor-supported version.",
    "expected": {
      "type": "equals",
      "value": "Compliant"
    },
    "platform": "windows",
    "vuln_id": "V-214359"
  },
  "check_content_excerpt": "Determine the version of the Apache software that is running on the system.\n\nIn a command line, navigate to \"<'INSTALLED PATH'>\\bin\". Run \"httpd -v\" to view the Apache version.\n\nIf the version of Apache is not at the following version or higher, this is a finding:\n\nApache 2.4 (February 2012)",
  "classification": "automated",
  "collector_commands": [],
  "collector_type": "platform_collector",
  "evaluator": "candidate_template",
  "evidence_fields": [
    "rule_id",
    "vuln_id",
    "status",
    "evidence",
    "source_artifact"
  ],
  "expected_values": {
    "type": "equals",
    "value": "Compliant"
  },
  "external_acceptance_refs": [],
  "fix_text_excerpt": "Install the current version of the web server software and maintain appropriate service packs and patches.",
  "fixtures": [],
  "implementation_status": "planned",
  "na_conditions": [],
  "normalizer": "command_output",
  "remediation": "planned",
  "rule_id": "SV-214359r961863_rule",
  "severity": "high",
  "source_benchmark": "",
  "source_coverage_manifest": "content/coverage/disa-authoritative/apache_server_2_4_windows_server_stig/u_apache_server_2_4_windows_y26m04_stig.json",
  "source_version": "U_Apache_Server_2-4_Windows_Y26M04_STIG.zip",
  "stig_id": "Apache_Server_2-4_Windows_Server_STIG",
  "title": "The Apache web server software must be a vendor-supported version.",
  "tracking_issue": "TODO-V-214359",
  "vuln_id": "V-214359"
}
