{
  "candidate_check": {
    "check": {
      "command": "powershell -NoProfile -Command \"Test-Path \\\"$env:windir\\System32\\tftp.exe\\\"\"",
      "type": "command_output"
    },
    "description": "The TFTP Client must not be installed on the system.",
    "expected": {
      "type": "equals",
      "value": "False"
    },
    "platform": "windows",
    "vuln_id": "V-253279"
  },
  "check_content_excerpt": "Verify TFTP Client has not been installed.\n\nNavigate to the Windows\\System32 directory.\n\nIf the \"TFTP\" application exists, this is a finding.",
  "classification": "automated",
  "collector_commands": [],
  "collector_type": "platform_collector",
  "evaluator": "candidate_template",
  "evidence_fields": [
    "rule_id",
    "vuln_id",
    "status",
    "evidence",
    "source_artifact"
  ],
  "expected_values": {
    "type": "equals",
    "value": "False"
  },
  "external_acceptance_refs": [],
  "fix_text_excerpt": "Uninstall \"TFTP Client\" from the system.\n\nRun \"Programs and Features\".\nSelect \"Turn Windows Features on or off\".\nDe-select \"TFTP Client\".",
  "fixtures": [],
  "implementation_status": "planned",
  "na_conditions": [],
  "normalizer": "command_output",
  "remediation": "planned",
  "rule_id": "SV-253279r958480_rule",
  "severity": "medium",
  "source_benchmark": "",
  "source_coverage_manifest": "content/coverage/disa-authoritative/microsoft_windows_11_stig/u_ms_windows_11_v2r6_stig.json",
  "source_version": "U_MS_Windows_11_V2R6_STIG.zip",
  "stig_id": "Microsoft_Windows_11_STIG",
  "title": "The TFTP Client must not be installed on the system.",
  "tracking_issue": "TODO-V-253279",
  "vuln_id": "V-253279"
}
