{
  "stig_id": "Google_Chrome_Linux_STIG",
  "platform": "linux",
  "version": "1.0.0",
  "checks": [
    { "vuln_id": "V-290001", "platform": "linux", "check": { "type": "file_content", "path": "/etc/opt/chrome/policies/managed/policy.json", "pattern": "\"AutoplayAllowed\":\\s*false", "is_regex": true }, "expected": { "type": "is_true" }, "description": "Chrome autoplay must be disabled" },
    { "vuln_id": "V-290002", "platform": "linux", "check": { "type": "file_content", "path": "/etc/opt/chrome/policies/managed/policy.json", "pattern": "\"DefaultPopupsSetting\":\\s*2", "is_regex": true }, "expected": { "type": "is_true" }, "description": "Chrome must block pop-ups by default" },
    { "vuln_id": "V-290003", "platform": "linux", "check": { "type": "file_content", "path": "/etc/opt/chrome/policies/managed/policy.json", "pattern": "\"PasswordManagerEnabled\":\\s*false", "is_regex": true }, "expected": { "type": "is_true" }, "description": "Chrome password manager must be disabled" },
    { "vuln_id": "V-290004", "platform": "linux", "check": { "type": "file_content", "path": "/etc/opt/chrome/policies/managed/policy.json", "pattern": "\"AutofillAddressEnabled\":\\s*false", "is_regex": true }, "expected": { "type": "is_true" }, "description": "Chrome autofill for addresses must be disabled" },
    { "vuln_id": "V-290005", "platform": "linux", "check": { "type": "file_content", "path": "/etc/opt/chrome/policies/managed/policy.json", "pattern": "\"AutofillCreditCardEnabled\":\\s*false", "is_regex": true }, "expected": { "type": "is_true" }, "description": "Chrome autofill for credit cards must be disabled" },
    { "vuln_id": "V-290006", "platform": "linux", "check": { "type": "file_content", "path": "/etc/opt/chrome/policies/managed/policy.json", "pattern": "\"SSLVersionMin\":\\s*\"tls1\\.2\"", "is_regex": true }, "expected": { "type": "is_true" }, "description": "Chrome minimum SSL version must be set to TLS 1.2" },
    { "vuln_id": "V-290007", "platform": "linux", "check": { "type": "file_content", "path": "/etc/opt/chrome/policies/managed/policy.json", "pattern": "\"SafeBrowsingProtectionLevel\":\\s*[12]", "is_regex": true }, "expected": { "type": "is_true" }, "description": "Chrome Safe Browsing must be enabled" },
    { "vuln_id": "V-290008", "platform": "linux", "check": { "type": "file_content", "path": "/etc/opt/chrome/policies/managed/policy.json", "pattern": "\"MetricsReportingEnabled\":\\s*false", "is_regex": true }, "expected": { "type": "is_true" }, "description": "Chrome metrics reporting must be disabled" },
    { "vuln_id": "V-290009", "platform": "linux", "check": { "type": "file_content", "path": "/etc/opt/chrome/policies/managed/policy.json", "pattern": "\"BrowserSignin\":\\s*0", "is_regex": true }, "expected": { "type": "is_true" }, "description": "Chrome browser sign-in must be disabled" },
    { "vuln_id": "V-290010", "platform": "linux", "check": { "type": "file_content", "path": "/etc/opt/chrome/policies/managed/policy.json", "pattern": "\"SyncDisabled\":\\s*true", "is_regex": true }, "expected": { "type": "is_true" }, "description": "Chrome sync must be disabled" },
    { "vuln_id": "V-290011", "platform": "linux", "check": { "type": "file_content", "path": "/etc/opt/chrome/policies/managed/policy.json", "pattern": "\"DefaultGeolocationSetting\":\\s*2", "is_regex": true }, "expected": { "type": "is_true" }, "description": "Chrome must block geolocation by default" },
    { "vuln_id": "V-290012", "platform": "linux", "check": { "type": "file_content", "path": "/etc/opt/chrome/policies/managed/policy.json", "pattern": "\"DefaultNotificationsSetting\":\\s*2", "is_regex": true }, "expected": { "type": "is_true" }, "description": "Chrome must block notifications by default" },
    { "vuln_id": "V-290013", "platform": "linux", "check": { "type": "file_content", "path": "/etc/opt/chrome/policies/managed/policy.json", "pattern": "\"SearchSuggestEnabled\":\\s*false", "is_regex": true }, "expected": { "type": "is_true" }, "description": "Chrome search suggestions must be disabled" },
    { "vuln_id": "V-290014", "platform": "linux", "check": { "type": "file_content", "path": "/etc/opt/chrome/policies/managed/policy.json", "pattern": "\"BlockThirdPartyCookies\":\\s*true", "is_regex": true }, "expected": { "type": "is_true" }, "description": "Chrome must block third-party cookies" },
    { "vuln_id": "V-290015", "platform": "linux", "check": { "type": "file_content", "path": "/etc/opt/chrome/policies/managed/policy.json", "pattern": "\"IncognitoModeAvailability\":\\s*1", "is_regex": true }, "expected": { "type": "is_true" }, "description": "Chrome incognito mode must be disabled" }
  ]
}
